humanfuzz/__init__.py
humanfuzz/analyzer.py
humanfuzz/browser.py
humanfuzz/cli.py
humanfuzz/cli_advanced.py
humanfuzz/cli_main.py
humanfuzz/discovery.py
humanfuzz/fuzzer.py
humanfuzz/reporter.py
humanfuzz/universal_scanner.py
humanfuzz/payloads/__init__.py
humanfuzz/payloads/csrf.py
humanfuzz/payloads/sqli.py
humanfuzz/payloads/ssrf.py
humanfuzz/payloads/xss.py
humanfuzz-1.0.0.dist-info/licenses/LICENSE
humanfuzz-1.0.0.dist-info/METADATA
humanfuzz-1.0.0.dist-info/WHEEL
humanfuzz-1.0.0.dist-info/entry_points.txt
humanfuzz-1.0.0.dist-info/top_level.txt
humanfuzz-1.0.0.dist-info/RECORD
