Metadata-Version: 2.4
Name: humanfuzz
Version: 1.0.0
Summary: A human-like web application fuzzing library that simulates real user interactions to discover security vulnerabilities
Home-page: https://github.com/zinzied/humanfuzz
Author: zinzied
Author-email: Ziedboughdir@gmail.com
Classifier: Programming Language :: Python :: 3
Classifier: License :: OSI Approved :: MIT License
Classifier: Operating System :: OS Independent
Classifier: Development Status :: 4 - Beta
Classifier: Intended Audience :: Developers
Classifier: Intended Audience :: Information Technology
Classifier: Topic :: Security
Classifier: Topic :: Software Development :: Testing
Requires-Python: >=3.8
License-File: LICENSE
Requires-Dist: playwright>=1.30.0
Requires-Dist: beautifulsoup4>=4.10.0
Requires-Dist: requests>=2.27.1
Requires-Dist: rich>=12.0.0
Requires-Dist: click>=8.0.0
Requires-Dist: pydantic>=1.9.0
Provides-Extra: enhanced
Requires-Dist: cloudscraper25; extra == "enhanced"
Requires-Dist: urllib4-enhanced; extra == "enhanced"
Dynamic: author
Dynamic: author-email
Dynamic: classifier
Dynamic: description
Dynamic: description-content-type
Dynamic: home-page
Dynamic: license-file
Dynamic: provides-extra
Dynamic: requires-dist
Dynamic: requires-python
Dynamic: summary
